{
    "@context": [
        "http://iiif.io/api/presentation/2/context.json",
        "http://codh.rois.ac.jp/iiif/curation/1/context.json"
    ],
    "@id": "https://nakamura196.github.io/suikeichuuzu/iiif-curation/jouzu06_heijou.json",
    "@type": "cr:Curation",
    "label": "jouzu06_heijou",
    "related": {
        "@id": "https://nakamura196.github.io/suikeichuuzu/asset/legend.pdf",
        "@type": "cr:MarkerLegend"
    },
    "selections": [
        {
            "@id": "https://nakamura196.github.io/suikeichuuzu/iiif/jouzu06_heijou/manifest.json/range",
            "@type": "sc:Range",
            "label": "jouzu06_heijou",
            "members": [
                {
                    "@id": "https://nakamura196.github.io/suikeichuuzu/iiif/jouzu06_heijou/manifest.json/canvas/p1#xywh=1570,67,81,191",
                    "@type": "sc:Canvas",
                    "label": "CTPC(a)0-01",
                    "metadata": [
                        {
                            "label": "Description",
                            "value": "[ <a href=\"https://suikeichu.web.app/item/CTPC(a)0-01\">魏高祖陵</a> ]<br/>分類：地点<br/>記号説明：亭台跡"
                        }
                    ],
                    "thumbnail": "https://iiif.dl.itc.u-tokyo.ac.jp/iiif/tmp/toyo/suikei/jouzu06_heijou.tif/1570,67,81,191/200,/0/default.jpg"
                },
                {
                    "@id": "https://nakamura196.github.io/suikeichuuzu/iiif/jouzu06_heijou/manifest.json/canvas/p1#xywh=1489,32,77,228",
                    "@type": "sc:Canvas",
                    "label": "CTPC(a)0-02",
                    "metadata": [
                        {
                            "label": "Description",
                            "value": "[ <a href=\"https://suikeichu.web.app/item/CTPC(a)0-02\">魏文明太后陵</a> ]<br/>分類：地点<br/>記号説明：亭台跡"
                        }
                    ],
                    "thumbnail": "https://iiif.dl.itc.u-tokyo.ac.jp/iiif/tmp/toyo/suikei/jouzu06_heijou.tif/1489,32,77,228/200,/0/default.jpg"
                },
                {
                    "@id": "https://nakamura196.github.io/suikeichuuzu/iiif/jouzu06_heijou/manifest.json/canvas/p1#xywh=1586,264,175,65",
                    "@type": "sc:Canvas",
                    "label": "CTPC(a)0-03",
                    "metadata": [
                        {
                            "label": "Description",
                            "value": "[ <a href=\"https://suikeichu.web.app/item/CTPC(a)0-03\">永固堂</a> ]<br/>分類：地点<br/>記号説明：亭台跡"
                        }
                    ],
                    "thumbnail": "https://iiif.dl.itc.u-tokyo.ac.jp/iiif/tmp/toyo/suikei/jouzu06_heijou.tif/1586,264,175,65/200,/0/default.jpg"
                },
                {
                    "@id": "https://nakamura196.github.io/suikeichuuzu/iiif/jouzu06_heijou/manifest.json/canvas/p1#xywh=1485,329,121,69",
                    "@type": "sc:Canvas",
                    "label": "CTPC(a)0-04",
                    "metadata": [
                        {
                            "label": "Description",
                            "value": "[ <a href=\"https://suikeichu.web.app/item/CTPC(a)0-04\">方山</a> ]<br/>分類：地点<br/>記号説明：亭台跡"
                        }
                    ],
                    "thumbnail": "https://iiif.dl.itc.u-tokyo.ac.jp/iiif/tmp/toyo/suikei/jouzu06_heijou.tif/1485,329,121,69/200,/0/default.jpg"
                },
                {
                    "@id": "https://nakamura196.github.io/suikeichuuzu/iiif/jouzu06_heijou/manifest.json/canvas/p1#xywh=1354,32,107,220",
                    "@type": "sc:Canvas",
                    "label": "CTPC(a)0-05",
                    "metadata": [
                        {
                            "label": "Description",
                            "value": "[ <a href=\"https://suikeichu.web.app/item/CTPC(a)0-05\">如渾水</a> ]<br/>分類：地形<br/>記号説明：河川"
                        }
                    ],
                    "thumbnail": "https://iiif.dl.itc.u-tokyo.ac.jp/iiif/tmp/toyo/suikei/jouzu06_heijou.tif/1354,32,107,220/200,/0/default.jpg"
                },
                {
                    "@id": "https://nakamura196.github.io/suikeichuuzu/iiif/jouzu06_heijou/manifest.json/canvas/p1#xywh=1670,403,200,93",
                    "@type": "sc:Canvas",
                    "label": "CTPC(a)0-06",
                    "metadata": [
                        {
                            "label": "Description",
                            "value": "[ <a href=\"https://suikeichu.web.app/item/CTPC(a)0-06\">靈泉池</a> ]<br/>分類：地形<br/>記号説明：湖"
                        }
                    ],
                    "thumbnail": "https://iiif.dl.itc.u-tokyo.ac.jp/iiif/tmp/toyo/suikei/jouzu06_heijou.tif/1670,403,200,93/200,/0/default.jpg"
                },
                {
                    "@id": "https://nakamura196.github.io/suikeichuuzu/iiif/jouzu06_heijou/manifest.json/canvas/p1#xywh=1628,460,310,95",
                    "@type": "sc:Canvas",
                    "label": "CTPC(a)0-07",
                    "metadata": [
                        {
                            "label": "Description",
                            "value": "[ <a href=\"https://suikeichu.web.app/item/CTPC(a)0-07\">舊名白楊泉</a> ]<br/>分類：地形<br/>記号説明：湖"
                        }
                    ],
                    "thumbnail": "https://iiif.dl.itc.u-tokyo.ac.jp/iiif/tmp/toyo/suikei/jouzu06_heijou.tif/1628,460,310,95/200,/0/default.jpg"
                },
                {
                    "@id": "https://nakamura196.github.io/suikeichuuzu/iiif/jouzu06_heijou/manifest.json/canvas/p1#xywh=1477,443,101,79",
                    "@type": "sc:Canvas",
                    "label": "CTPC(a)0-08",
                    "metadata": [
                        {
                            "label": "Description",
                            "value": "[ <a href=\"https://suikeichu.web.app/item/CTPC(a)0-08\">枝津</a> ]<br/>分類：地形<br/>記号説明：河川"
                        }
                    ],
                    "thumbnail": "https://iiif.dl.itc.u-tokyo.ac.jp/iiif/tmp/toyo/suikei/jouzu06_heijou.tif/1477,443,101,79/200,/0/default.jpg"
                },
                {
                    "@id": "https://nakamura196.github.io/suikeichuuzu/iiif/jouzu06_heijou/manifest.json/canvas/p1#xywh=1291,554,147,89",
                    "@type": "sc:Canvas",
                    "label": "CTPC(a)0-09",
                    "metadata": [
                        {
                            "label": "Description",
                            "value": "[ <a href=\"https://suikeichu.web.app/item/CTPC(a)0-09\">北宮</a> ]<br/>分類：地点<br/>記号説明：亭台跡"
                        }
                    ],
                    "thumbnail": "https://iiif.dl.itc.u-tokyo.ac.jp/iiif/tmp/toyo/suikei/jouzu06_heijou.tif/1291,554,147,89/200,/0/default.jpg"
                },
                {
                    "@id": "https://nakamura196.github.io/suikeichuuzu/iiif/jouzu06_heijou/manifest.json/canvas/p1#xywh=1435,712,165,83",
                    "@type": "sc:Canvas",
                    "label": "CTPC(a)0-10",
                    "metadata": [
                        {
                            "label": "Description",
                            "value": "[ <a href=\"https://suikeichu.web.app/item/CTPC(a)0-10\">北苑</a> ]<br/>分類：地形<br/>記号説明：河川"
                        }
                    ],
                    "thumbnail": "https://iiif.dl.itc.u-tokyo.ac.jp/iiif/tmp/toyo/suikei/jouzu06_heijou.tif/1435,712,165,83/200,/0/default.jpg"
                },
                {
                    "@id": "https://nakamura196.github.io/suikeichuuzu/iiif/jouzu06_heijou/manifest.json/canvas/p1#xywh=397,955,179,83",
                    "@type": "sc:Canvas",
                    "label": "CTPC(a)0-11",
                    "metadata": [
                        {
                            "label": "Description",
                            "value": "[ <a href=\"https://suikeichu.web.app/item/CTPC(a)0-11\">北苑</a> ]<br/>分類：地形<br/>記号説明：河川"
                        }
                    ],
                    "thumbnail": "https://iiif.dl.itc.u-tokyo.ac.jp/iiif/tmp/toyo/suikei/jouzu06_heijou.tif/397,955,179,83/200,/0/default.jpg"
                },
                {
                    "@id": "https://nakamura196.github.io/suikeichuuzu/iiif/jouzu06_heijou/manifest.json/canvas/p1#xywh=1509,834,196,95",
                    "@type": "sc:Canvas",
                    "label": "CTPC(a)0-12",
                    "metadata": [
                        {
                            "label": "Description",
                            "value": "[ <a href=\"https://suikeichu.web.app/item/CTPC(a)0-12\">白登臺</a> ]<br/>分類：地点<br/>記号説明：亭台跡"
                        }
                    ],
                    "thumbnail": "https://iiif.dl.itc.u-tokyo.ac.jp/iiif/tmp/toyo/suikei/jouzu06_heijou.tif/1509,834,196,95/200,/0/default.jpg"
                },
                {
                    "@id": "https://nakamura196.github.io/suikeichuuzu/iiif/jouzu06_heijou/manifest.json/canvas/p1#xywh=1507,963,202,89",
                    "@type": "sc:Canvas",
                    "label": "CTPC(a)0-13",
                    "metadata": [
                        {
                            "label": "Description",
                            "value": "[ <a href=\"https://suikeichu.web.app/item/CTPC(a)0-13\">白登山</a> ]<br/>分類：地点<br/>記号説明：亭台跡"
                        }
                    ],
                    "thumbnail": "https://iiif.dl.itc.u-tokyo.ac.jp/iiif/tmp/toyo/suikei/jouzu06_heijou.tif/1507,963,202,89/200,/0/default.jpg"
                },
                {
                    "@id": "https://nakamura196.github.io/suikeichuuzu/iiif/jouzu06_heijou/manifest.json/canvas/p1#xywh=467,1149,91,75",
                    "@type": "sc:Canvas",
                    "label": "CTPC(a)0-14",
                    "metadata": [
                        {
                            "label": "Description",
                            "value": "[ <a href=\"https://suikeichu.web.app/item/CTPC(a)0-14\">池</a> ]<br/>分類：地形<br/>記号説明：湖"
                        }
                    ],
                    "thumbnail": "https://iiif.dl.itc.u-tokyo.ac.jp/iiif/tmp/toyo/suikei/jouzu06_heijou.tif/467,1149,91,75/200,/0/default.jpg"
                },
                {
                    "@id": "https://nakamura196.github.io/suikeichuuzu/iiif/jouzu06_heijou/manifest.json/canvas/p1#xywh=378,1197,83,85",
                    "@type": "sc:Canvas",
                    "label": "CTPC(a)0-15",
                    "metadata": [
                        {
                            "label": "Description",
                            "value": "[ <a href=\"https://suikeichu.web.app/item/CTPC(a)0-15\">沼</a> ]<br/>分類：地形<br/>記号説明：湖"
                        }
                    ],
                    "thumbnail": "https://iiif.dl.itc.u-tokyo.ac.jp/iiif/tmp/toyo/suikei/jouzu06_heijou.tif/378,1197,83,85/200,/0/default.jpg"
                },
                {
                    "@id": "https://nakamura196.github.io/suikeichuuzu/iiif/jouzu06_heijou/manifest.json/canvas/p1#xywh=298,1357,153,91",
                    "@type": "sc:Canvas",
                    "label": "CTPC(a)0-16",
                    "metadata": [
                        {
                            "label": "Description",
                            "value": "[ <a href=\"https://suikeichu.web.app/item/CTPC(a)0-16\">虎圏</a> ]<br/>分類：地点<br/>記号説明：亭台跡"
                        }
                    ],
                    "thumbnail": "https://iiif.dl.itc.u-tokyo.ac.jp/iiif/tmp/toyo/suikei/jouzu06_heijou.tif/298,1357,153,91/200,/0/default.jpg"
                },
                {
                    "@id": "https://nakamura196.github.io/suikeichuuzu/iiif/jouzu06_heijou/manifest.json/canvas/p1#xywh=1054,1181,371,93",
                    "@type": "sc:Canvas",
                    "label": "CTPC(a)0-17",
                    "metadata": [
                        {
                            "label": "Description",
                            "value": "[ <a href=\"https://suikeichu.web.app/item/CTPC(a)0-17\">北魏舊京城</a> ]<br/>分類：なし<br/>記号説明："
                        }
                    ],
                    "thumbnail": "https://iiif.dl.itc.u-tokyo.ac.jp/iiif/tmp/toyo/suikei/jouzu06_heijou.tif/1054,1181,371,93/200,/0/default.jpg"
                },
                {
                    "@id": "https://nakamura196.github.io/suikeichuuzu/iiif/jouzu06_heijou/manifest.json/canvas/p1#xywh=1513,1282,89,200",
                    "@type": "sc:Canvas",
                    "label": "CTPC(a)0-18",
                    "metadata": [
                        {
                            "label": "Description",
                            "value": "[ <a href=\"https://suikeichu.web.app/item/CTPC(a)0-18\">兩石柱</a> ]<br/>分類：地点<br/>記号説明：亭台跡"
                        }
                    ],
                    "thumbnail": "https://iiif.dl.itc.u-tokyo.ac.jp/iiif/tmp/toyo/suikei/jouzu06_heijou.tif/1513,1282,89,200/200,/0/default.jpg"
                },
                {
                    "@id": "https://nakamura196.github.io/suikeichuuzu/iiif/jouzu06_heijou/manifest.json/canvas/p1#xywh=1420,1274,85,206",
                    "@type": "sc:Canvas",
                    "label": "CTPC(a)0-19",
                    "metadata": [
                        {
                            "label": "Description",
                            "value": "[ <a href=\"https://suikeichu.web.app/item/CTPC(a)0-19\">寍先宮</a> ]<br/>分類：地点<br/>記号説明：亭台跡"
                        }
                    ],
                    "thumbnail": "https://iiif.dl.itc.u-tokyo.ac.jp/iiif/tmp/toyo/suikei/jouzu06_heijou.tif/1420,1274,85,206/200,/0/default.jpg"
                },
                {
                    "@id": "https://nakamura196.github.io/suikeichuuzu/iiif/jouzu06_heijou/manifest.json/canvas/p1#xywh=1870,1665,105,238",
                    "@type": "sc:Canvas",
                    "label": "CTPC(a)0-20",
                    "metadata": [
                        {
                            "label": "Description",
                            "value": "[ <a href=\"https://suikeichu.web.app/item/CTPC(a)0-20\">靜輪宮</a> ]<br/>分類：地点<br/>記号説明：亭台跡"
                        }
                    ],
                    "thumbnail": "https://iiif.dl.itc.u-tokyo.ac.jp/iiif/tmp/toyo/suikei/jouzu06_heijou.tif/1870,1665,105,238/200,/0/default.jpg"
                },
                {
                    "@id": "https://nakamura196.github.io/suikeichuuzu/iiif/jouzu06_heijou/manifest.json/canvas/p1#xywh=1850,1961,93,310",
                    "@type": "sc:Canvas",
                    "label": "CTPC(a)0-21",
                    "metadata": [
                        {
                            "label": "Description",
                            "value": "[ <a href=\"https://suikeichu.web.app/item/CTPC(a)0-21\">大道壇廟</a> ]<br/>分類：地点<br/>記号説明：亭台跡"
                        }
                    ],
                    "thumbnail": "https://iiif.dl.itc.u-tokyo.ac.jp/iiif/tmp/toyo/suikei/jouzu06_heijou.tif/1850,1961,93,310/200,/0/default.jpg"
                },
                {
                    "@id": "https://nakamura196.github.io/suikeichuuzu/iiif/jouzu06_heijou/manifest.json/canvas/p1#xywh=1709,1963,105,286",
                    "@type": "sc:Canvas",
                    "label": "CTPC(a)0-22",
                    "metadata": [
                        {
                            "label": "Description",
                            "value": "[ <a href=\"https://suikeichu.web.app/item/CTPC(a)0-22\">三層浮圖</a> ]<br/>分類：地点<br/>記号説明：亭台跡"
                        }
                    ],
                    "thumbnail": "https://iiif.dl.itc.u-tokyo.ac.jp/iiif/tmp/toyo/suikei/jouzu06_heijou.tif/1709,1963,105,286/200,/0/default.jpg"
                },
                {
                    "@id": "https://nakamura196.github.io/suikeichuuzu/iiif/jouzu06_heijou/manifest.json/canvas/p1#xywh=1181,1522,288,107",
                    "@type": "sc:Canvas",
                    "label": "CTPC(a)0-23",
                    "metadata": [
                        {
                            "label": "Description",
                            "value": "[ <a href=\"https://suikeichu.web.app/item/CTPC(a)0-23\">平城故城</a> ]<br/>分類：なし<br/>記号説明："
                        }
                    ],
                    "thumbnail": "https://iiif.dl.itc.u-tokyo.ac.jp/iiif/tmp/toyo/suikei/jouzu06_heijou.tif/1181,1522,288,107/200,/0/default.jpg"
                },
                {
                    "@id": "https://nakamura196.github.io/suikeichuuzu/iiif/jouzu06_heijou/manifest.json/canvas/p1#xywh=1487,1631,145,93",
                    "@type": "sc:Canvas",
                    "label": "CTPC(a)0-24",
                    "metadata": [
                        {
                            "label": "Description",
                            "value": "[ <a href=\"https://suikeichu.web.app/item/CTPC(a)0-24\">端門</a> ]<br/>分類：地点<br/>記号説明：長城門"
                        }
                    ],
                    "thumbnail": "https://iiif.dl.itc.u-tokyo.ac.jp/iiif/tmp/toyo/suikei/jouzu06_heijou.tif/1487,1631,145,93/200,/0/default.jpg"
                },
                {
                    "@id": "https://nakamura196.github.io/suikeichuuzu/iiif/jouzu06_heijou/manifest.json/canvas/p1#xywh=1249,1633,177,93",
                    "@type": "sc:Canvas",
                    "label": "CTPC(a)0-25",
                    "metadata": [
                        {
                            "label": "Description",
                            "value": "[ <a href=\"https://suikeichu.web.app/item/CTPC(a)0-25\">中陽門</a> ]<br/>分類：地点<br/>記号説明：長城門"
                        }
                    ],
                    "thumbnail": "https://iiif.dl.itc.u-tokyo.ac.jp/iiif/tmp/toyo/suikei/jouzu06_heijou.tif/1249,1633,177,93/200,/0/default.jpg"
                },
                {
                    "@id": "https://nakamura196.github.io/suikeichuuzu/iiif/jouzu06_heijou/manifest.json/canvas/p1#xywh=1011,1635,196,77",
                    "@type": "sc:Canvas",
                    "label": "CTPC(a)0-26",
                    "metadata": [
                        {
                            "label": "Description",
                            "value": "[ <a href=\"https://suikeichu.web.app/item/CTPC(a)0-26\">乾元門</a> ]<br/>分類：地点<br/>記号説明：長城門"
                        }
                    ],
                    "thumbnail": "https://iiif.dl.itc.u-tokyo.ac.jp/iiif/tmp/toyo/suikei/jouzu06_heijou.tif/1011,1635,196,77/200,/0/default.jpg"
                },
                {
                    "@id": "https://nakamura196.github.io/suikeichuuzu/iiif/jouzu06_heijou/manifest.json/canvas/p1#xywh=1580,1719,81,230",
                    "@type": "sc:Canvas",
                    "label": "CTPC(a)0-27",
                    "metadata": [
                        {
                            "label": "Description",
                            "value": "[ <a href=\"https://suikeichu.web.app/item/CTPC(a)0-27\">東掖門</a> ]<br/>分類：地点<br/>記号説明：長城門"
                        }
                    ],
                    "thumbnail": "https://iiif.dl.itc.u-tokyo.ac.jp/iiif/tmp/toyo/suikei/jouzu06_heijou.tif/1580,1719,81,230/200,/0/default.jpg"
                },
                {
                    "@id": "https://nakamura196.github.io/suikeichuuzu/iiif/jouzu06_heijou/manifest.json/canvas/p1#xywh=1586,2002,85,218",
                    "@type": "sc:Canvas",
                    "label": "CTPC(a)0-28",
                    "metadata": [
                        {
                            "label": "Description",
                            "value": "[ <a href=\"https://suikeichu.web.app/item/CTPC(a)0-28\">雲龍門</a> ]<br/>分類：地点<br/>記号説明：長城門"
                        }
                    ],
                    "thumbnail": "https://iiif.dl.itc.u-tokyo.ac.jp/iiif/tmp/toyo/suikei/jouzu06_heijou.tif/1586,2002,85,218/200,/0/default.jpg"
                },
                {
                    "@id": "https://nakamura196.github.io/suikeichuuzu/iiif/jouzu06_heijou/manifest.json/canvas/p1#xywh=1473,1808,77,260",
                    "@type": "sc:Canvas",
                    "label": "CTPC(a)0-29",
                    "metadata": [
                        {
                            "label": "Description",
                            "value": "[ <a href=\"https://suikeichu.web.app/item/CTPC(a)0-29\">紫宮寺</a> ]<br/>分類：なし<br/>記号説明："
                        }
                    ],
                    "thumbnail": "https://iiif.dl.itc.u-tokyo.ac.jp/iiif/tmp/toyo/suikei/jouzu06_heijou.tif/1473,1808,77,260/200,/0/default.jpg"
                },
                {
                    "@id": "https://nakamura196.github.io/suikeichuuzu/iiif/jouzu06_heijou/manifest.json/canvas/p1#xywh=1425,1867,67,95",
                    "@type": "sc:Canvas",
                    "label": "CTPC(a)0-30",
                    "metadata": [
                        {
                            "label": "Description",
                            "value": "[ <a href=\"https://suikeichu.web.app/item/CTPC(a)0-30\">碑</a> ]<br/>分類：なし<br/>記号説明："
                        }
                    ],
                    "thumbnail": "https://iiif.dl.itc.u-tokyo.ac.jp/iiif/tmp/toyo/suikei/jouzu06_heijou.tif/1425,1867,67,95/200,/0/default.jpg"
                },
                {
                    "@id": "https://nakamura196.github.io/suikeichuuzu/iiif/jouzu06_heijou/manifest.json/canvas/p1#xywh=1372,1838,69,159",
                    "@type": "sc:Canvas",
                    "label": "CTPC(a)0-31",
                    "metadata": [
                        {
                            "label": "Description",
                            "value": "[ <a href=\"https://suikeichu.web.app/item/CTPC(a)0-31\">東階</a> ]<br/>分類：なし<br/>記号説明："
                        }
                    ],
                    "thumbnail": "https://iiif.dl.itc.u-tokyo.ac.jp/iiif/tmp/toyo/suikei/jouzu06_heijou.tif/1372,1838,69,159/200,/0/default.jpg"
                },
                {
                    "@id": "https://nakamura196.github.io/suikeichuuzu/iiif/jouzu06_heijou/manifest.json/canvas/p1#xywh=1304,1808,81,198",
                    "@type": "sc:Canvas",
                    "label": "CTPC(a)0-32",
                    "metadata": [
                        {
                            "label": "Description",
                            "value": "[ <a href=\"https://suikeichu.web.app/item/CTPC(a)0-32\">太和殿</a> ]<br/>分類：なし<br/>記号説明："
                        }
                    ],
                    "thumbnail": "https://iiif.dl.itc.u-tokyo.ac.jp/iiif/tmp/toyo/suikei/jouzu06_heijou.tif/1304,1808,81,198/200,/0/default.jpg"
                },
                {
                    "@id": "https://nakamura196.github.io/suikeichuuzu/iiif/jouzu06_heijou/manifest.json/canvas/p1#xywh=1261,1834,67,167",
                    "@type": "sc:Canvas",
                    "label": "CTPC(a)0-33",
                    "metadata": [
                        {
                            "label": "Description",
                            "value": "[ <a href=\"https://suikeichu.web.app/item/CTPC(a)0-33\">東堂</a> ]<br/>分類：なし<br/>記号説明："
                        }
                    ],
                    "thumbnail": "https://iiif.dl.itc.u-tokyo.ac.jp/iiif/tmp/toyo/suikei/jouzu06_heijou.tif/1261,1834,67,167/200,/0/default.jpg"
                },
                {
                    "@id": "https://nakamura196.github.io/suikeichuuzu/iiif/jouzu06_heijou/manifest.json/canvas/p1#xywh=1185,1810,87,212",
                    "@type": "sc:Canvas",
                    "label": "CTPC(a)0-34",
                    "metadata": [
                        {
                            "label": "Description",
                            "value": "[ <a href=\"https://suikeichu.web.app/item/CTPC(a)0-34\">太極殿</a> ]<br/>分類：なし<br/>記号説明："
                        }
                    ],
                    "thumbnail": "https://iiif.dl.itc.u-tokyo.ac.jp/iiif/tmp/toyo/suikei/jouzu06_heijou.tif/1185,1810,87,212/200,/0/default.jpg"
                },
                {
                    "@id": "https://nakamura196.github.io/suikeichuuzu/iiif/jouzu06_heijou/manifest.json/canvas/p1#xywh=1126,1856,73,143",
                    "@type": "sc:Canvas",
                    "label": "CTPC(a)0-35",
                    "metadata": [
                        {
                            "label": "Description",
                            "value": "[ <a href=\"https://suikeichu.web.app/item/CTPC(a)0-35\">西堂</a> ]<br/>分類：なし<br/>記号説明："
                        }
                    ],
                    "thumbnail": "https://iiif.dl.itc.u-tokyo.ac.jp/iiif/tmp/toyo/suikei/jouzu06_heijou.tif/1126,1856,73,143/200,/0/default.jpg"
                },
                {
                    "@id": "https://nakamura196.github.io/suikeichuuzu/iiif/jouzu06_heijou/manifest.json/canvas/p1#xywh=1154,2002,157,77",
                    "@type": "sc:Canvas",
                    "label": "CTPC(a)0-36",
                    "metadata": [
                        {
                            "label": "Description",
                            "value": "[ <a href=\"https://suikeichu.web.app/item/CTPC(a)0-36\">朝堂</a> ]<br/>分類：なし<br/>記号説明："
                        }
                    ],
                    "thumbnail": "https://iiif.dl.itc.u-tokyo.ac.jp/iiif/tmp/toyo/suikei/jouzu06_heijou.tif/1154,2002,157,77/200,/0/default.jpg"
                },
                {
                    "@id": "https://nakamura196.github.io/suikeichuuzu/iiif/jouzu06_heijou/manifest.json/canvas/p1#xywh=1261,2062,95,143",
                    "@type": "sc:Canvas",
                    "label": "CTPC(a)0-37",
                    "metadata": [
                        {
                            "label": "Description",
                            "value": "[ <a href=\"https://suikeichu.web.app/item/CTPC(a)0-37\">象魏</a> ]<br/>分類：なし<br/>記号説明："
                        }
                    ],
                    "thumbnail": "https://iiif.dl.itc.u-tokyo.ac.jp/iiif/tmp/toyo/suikei/jouzu06_heijou.tif/1261,2062,95,143/200,/0/default.jpg"
                },
                {
                    "@id": "https://nakamura196.github.io/suikeichuuzu/iiif/jouzu06_heijou/manifest.json/canvas/p1#xywh=1130,2078,81,145",
                    "@type": "sc:Canvas",
                    "label": "CTPC(a)0-38",
                    "metadata": [
                        {
                            "label": "Description",
                            "value": "[ <a href=\"https://suikeichu.web.app/item/CTPC(a)0-38\">象魏</a> ]<br/>分類：なし<br/>記号説明："
                        }
                    ],
                    "thumbnail": "https://iiif.dl.itc.u-tokyo.ac.jp/iiif/tmp/toyo/suikei/jouzu06_heijou.tif/1130,2078,81,145/200,/0/default.jpg"
                },
                {
                    "@id": "https://nakamura196.github.io/suikeichuuzu/iiif/jouzu06_heijou/manifest.json/canvas/p1#xywh=953,1709,79,212",
                    "@type": "sc:Canvas",
                    "label": "CTPC(a)0-39",
                    "metadata": [
                        {
                            "label": "Description",
                            "value": "[ <a href=\"https://suikeichu.web.app/item/CTPC(a)0-39\">西掖門</a> ]<br/>分類：地点<br/>記号説明：長城門"
                        }
                    ],
                    "thumbnail": "https://iiif.dl.itc.u-tokyo.ac.jp/iiif/tmp/toyo/suikei/jouzu06_heijou.tif/953,1709,79,212/200,/0/default.jpg"
                },
                {
                    "@id": "https://nakamura196.github.io/suikeichuuzu/iiif/jouzu06_heijou/manifest.json/canvas/p1#xywh=957,1981,95,236",
                    "@type": "sc:Canvas",
                    "label": "CTPC(a)0-40",
                    "metadata": [
                        {
                            "label": "Description",
                            "value": "[ <a href=\"https://suikeichu.web.app/item/CTPC(a)0-40\">神虎門</a> ]<br/>分類：地点<br/>記号説明：長城門"
                        }
                    ],
                    "thumbnail": "https://iiif.dl.itc.u-tokyo.ac.jp/iiif/tmp/toyo/suikei/jouzu06_heijou.tif/957,1981,95,236/200,/0/default.jpg"
                },
                {
                    "@id": "https://nakamura196.github.io/suikeichuuzu/iiif/jouzu06_heijou/manifest.json/canvas/p1#xywh=1443,2231,208,95",
                    "@type": "sc:Canvas",
                    "label": "CTPC(a)0-41",
                    "metadata": [
                        {
                            "label": "Description",
                            "value": "[ <a href=\"https://suikeichu.web.app/item/CTPC(a)0-41\">承賢門</a> ]<br/>分類：地点<br/>記号説明：長城門"
                        }
                    ],
                    "thumbnail": "https://iiif.dl.itc.u-tokyo.ac.jp/iiif/tmp/toyo/suikei/jouzu06_heijou.tif/1443,2231,208,95/200,/0/default.jpg"
                },
                {
                    "@id": "https://nakamura196.github.io/suikeichuuzu/iiif/jouzu06_heijou/manifest.json/canvas/p1#xywh=1227,2227,195,97",
                    "@type": "sc:Canvas",
                    "label": "CTPC(a)0-42",
                    "metadata": [
                        {
                            "label": "Description",
                            "value": "[ <a href=\"https://suikeichu.web.app/item/CTPC(a)0-42\">中華門</a> ]<br/>分類：地点<br/>記号説明：長城門"
                        }
                    ],
                    "thumbnail": "https://iiif.dl.itc.u-tokyo.ac.jp/iiif/tmp/toyo/suikei/jouzu06_heijou.tif/1227,2227,195,97/200,/0/default.jpg"
                },
                {
                    "@id": "https://nakamura196.github.io/suikeichuuzu/iiif/jouzu06_heijou/manifest.json/canvas/p1#xywh=1529,2336,173,91",
                    "@type": "sc:Canvas",
                    "label": "CTPC(a)0-43",
                    "metadata": [
                        {
                            "label": "Description",
                            "value": "[ <a href=\"https://suikeichu.web.app/item/CTPC(a)0-43\">皇信堂</a> ]<br/>分類：地点<br/>記号説明：亭台跡"
                        }
                    ],
                    "thumbnail": "https://iiif.dl.itc.u-tokyo.ac.jp/iiif/tmp/toyo/suikei/jouzu06_heijou.tif/1529,2336,173,91/200,/0/default.jpg"
                },
                {
                    "@id": "https://nakamura196.github.io/suikeichuuzu/iiif/jouzu06_heijou/manifest.json/canvas/p1#xywh=1487,2467,147,81",
                    "@type": "sc:Canvas",
                    "label": "CTPC(a)0-44",
                    "metadata": [
                        {
                            "label": "Description",
                            "value": "[ <a href=\"https://suikeichu.web.app/item/CTPC(a)0-44\">白臺</a> ]<br/>分類：地点<br/>記号説明：亭台跡"
                        }
                    ],
                    "thumbnail": "https://iiif.dl.itc.u-tokyo.ac.jp/iiif/tmp/toyo/suikei/jouzu06_heijou.tif/1487,2467,147,81/200,/0/default.jpg"
                },
                {
                    "@id": "https://nakamura196.github.io/suikeichuuzu/iiif/jouzu06_heijou/manifest.json/canvas/p1#xywh=1251,2413,212,95",
                    "@type": "sc:Canvas",
                    "label": "CTPC(a)0-45",
                    "metadata": [
                        {
                            "label": "Description",
                            "value": "[ <a href=\"https://suikeichu.web.app/item/CTPC(a)0-45\">朱明閣</a> ]<br/>分類：地点<br/>記号説明：亭台跡"
                        }
                    ],
                    "thumbnail": "https://iiif.dl.itc.u-tokyo.ac.jp/iiif/tmp/toyo/suikei/jouzu06_heijou.tif/1251,2413,212,95/200,/0/default.jpg"
                },
                {
                    "@id": "https://nakamura196.github.io/suikeichuuzu/iiif/jouzu06_heijou/manifest.json/canvas/p1#xywh=1169,2592,177,97",
                    "@type": "sc:Canvas",
                    "label": "CTPC(a)0-46",
                    "metadata": [
                        {
                            "label": "Description",
                            "value": "[ <a href=\"https://suikeichu.web.app/item/CTPC(a)0-46\">御路</a> ]<br/>分類：地形<br/>記号説明：河川"
                        }
                    ],
                    "thumbnail": "https://iiif.dl.itc.u-tokyo.ac.jp/iiif/tmp/toyo/suikei/jouzu06_heijou.tif/1169,2592,177,97/200,/0/default.jpg"
                },
                {
                    "@id": "https://nakamura196.github.io/suikeichuuzu/iiif/jouzu06_heijou/manifest.json/canvas/p1#xywh=1358,2608,123,93",
                    "@type": "sc:Canvas",
                    "label": "CTPC(a)0-47",
                    "metadata": [
                        {
                            "label": "Description",
                            "value": "[ <a href=\"https://suikeichu.web.app/item/CTPC(a)0-47\">蓬臺</a> ]<br/>分類：地点<br/>記号説明：亭台跡"
                        }
                    ],
                    "thumbnail": "https://iiif.dl.itc.u-tokyo.ac.jp/iiif/tmp/toyo/suikei/jouzu06_heijou.tif/1358,2608,123,93/200,/0/default.jpg"
                },
                {
                    "@id": "https://nakamura196.github.io/suikeichuuzu/iiif/jouzu06_heijou/manifest.json/canvas/p1#xywh=1360,2677,125,67",
                    "@type": "sc:Canvas",
                    "label": "CTPC(a)0-48",
                    "metadata": [
                        {
                            "label": "Description",
                            "value": "[ <a href=\"https://suikeichu.web.app/item/CTPC(a)0-48\">白樓</a> ]<br/>分類：地点<br/>記号説明：亭台跡"
                        }
                    ],
                    "thumbnail": "https://iiif.dl.itc.u-tokyo.ac.jp/iiif/tmp/toyo/suikei/jouzu06_heijou.tif/1360,2677,125,67/200,/0/default.jpg"
                },
                {
                    "@id": "https://nakamura196.github.io/suikeichuuzu/iiif/jouzu06_heijou/manifest.json/canvas/p1#xywh=1364,2731,145,83",
                    "@type": "sc:Canvas",
                    "label": "CTPC(a)0-49",
                    "metadata": [
                        {
                            "label": "Description",
                            "value": "[ <a href=\"https://suikeichu.web.app/item/CTPC(a)0-49\">皇舅寺</a> ]<br/>分類：地点<br/>記号説明：亭台跡"
                        }
                    ],
                    "thumbnail": "https://iiif.dl.itc.u-tokyo.ac.jp/iiif/tmp/toyo/suikei/jouzu06_heijou.tif/1364,2731,145,83/200,/0/default.jpg"
                },
                {
                    "@id": "https://nakamura196.github.io/suikeichuuzu/iiif/jouzu06_heijou/manifest.json/canvas/p1#xywh=1346,2733,363,161",
                    "@type": "sc:Canvas",
                    "label": "CTPC(a)0-50",
                    "metadata": [
                        {
                            "label": "Description",
                            "value": "[ <a href=\"https://suikeichu.web.app/item/CTPC(a)0-50\">永寍七級浮圖</a> ]<br/>分類：地点<br/>記号説明：亭台跡"
                        }
                    ],
                    "thumbnail": "https://iiif.dl.itc.u-tokyo.ac.jp/iiif/tmp/toyo/suikei/jouzu06_heijou.tif/1346,2733,363,161/200,/0/default.jpg"
                },
                {
                    "@id": "https://nakamura196.github.io/suikeichuuzu/iiif/jouzu06_heijou/manifest.json/canvas/p1#xywh=2142,1953,141,93",
                    "@type": "sc:Canvas",
                    "label": "CTPC(a)0-51",
                    "metadata": [
                        {
                            "label": "Description",
                            "value": "[ <a href=\"https://suikeichu.web.app/item/CTPC(a)0-51\">東皋</a> ]<br/>分類：地点<br/>記号説明：亭台跡"
                        }
                    ],
                    "thumbnail": "https://iiif.dl.itc.u-tokyo.ac.jp/iiif/tmp/toyo/suikei/jouzu06_heijou.tif/2142,1953,141,93/200,/0/default.jpg"
                },
                {
                    "@id": "https://nakamura196.github.io/suikeichuuzu/iiif/jouzu06_heijou/manifest.json/canvas/p1#xywh=2029,1963,83,198",
                    "@type": "sc:Canvas",
                    "label": "CTPC(a)0-52",
                    "metadata": [
                        {
                            "label": "Description",
                            "value": "[ <a href=\"https://suikeichu.web.app/item/CTPC(a)0-52\">東郭</a> ]<br/>分類：なし<br/>記号説明："
                        }
                    ],
                    "thumbnail": "https://iiif.dl.itc.u-tokyo.ac.jp/iiif/tmp/toyo/suikei/jouzu06_heijou.tif/2029,1963,83,198/200,/0/default.jpg"
                },
                {
                    "@id": "https://nakamura196.github.io/suikeichuuzu/iiif/jouzu06_heijou/manifest.json/canvas/p1#xywh=2124,2058,159,343",
                    "@type": "sc:Canvas",
                    "label": "CTPC(a)0-53",
                    "metadata": [
                        {
                            "label": "Description",
                            "value": "[ <a href=\"https://suikeichu.web.app/item/CTPC(a)0-53\">鉗耳慶時所立祗洹舎</a> ]<br/>分類：地点<br/>記号説明：亭台跡"
                        }
                    ],
                    "thumbnail": "https://iiif.dl.itc.u-tokyo.ac.jp/iiif/tmp/toyo/suikei/jouzu06_heijou.tif/2124,2058,159,343/200,/0/default.jpg"
                },
                {
                    "@id": "https://nakamura196.github.io/suikeichuuzu/iiif/jouzu06_heijou/manifest.json/canvas/p1#xywh=334,1484,99,159",
                    "@type": "sc:Canvas",
                    "label": "CTPC(a)0-54",
                    "metadata": [
                        {
                            "label": "Description",
                            "value": "[ <a href=\"https://suikeichu.web.app/item/CTPC(a)0-54\">西郭</a> ]<br/>分類：なし<br/>記号説明："
                        }
                    ],
                    "thumbnail": "https://iiif.dl.itc.u-tokyo.ac.jp/iiif/tmp/toyo/suikei/jouzu06_heijou.tif/334,1484,99,159/200,/0/default.jpg"
                },
                {
                    "@id": "https://nakamura196.github.io/suikeichuuzu/iiif/jouzu06_heijou/manifest.json/canvas/p1#xywh=237,1480,95,210",
                    "@type": "sc:Canvas",
                    "label": "CTPC(a)0-55",
                    "metadata": [
                        {
                            "label": "Description",
                            "value": "[ <a href=\"https://suikeichu.web.app/item/CTPC(a)0-55\">郊天碑</a> ]<br/>分類：地点<br/>記号説明：亭台跡"
                        }
                    ],
                    "thumbnail": "https://iiif.dl.itc.u-tokyo.ac.jp/iiif/tmp/toyo/suikei/jouzu06_heijou.tif/237,1480,95,210/200,/0/default.jpg"
                },
                {
                    "@id": "https://nakamura196.github.io/suikeichuuzu/iiif/jouzu06_heijou/manifest.json/canvas/p1#xywh=141,1490,91,216",
                    "@type": "sc:Canvas",
                    "label": "CTPC(a)0-56",
                    "metadata": [
                        {
                            "label": "Description",
                            "value": "[ <a href=\"https://suikeichu.web.app/item/CTPC(a)0-56\">郊天壇</a> ]<br/>分類：地点<br/>記号説明：亭台跡"
                        }
                    ],
                    "thumbnail": "https://iiif.dl.itc.u-tokyo.ac.jp/iiif/tmp/toyo/suikei/jouzu06_heijou.tif/141,1490,91,216/200,/0/default.jpg"
                },
                {
                    "@id": "https://nakamura196.github.io/suikeichuuzu/iiif/jouzu06_heijou/manifest.json/canvas/p1#xywh=1943,2737,87,145",
                    "@type": "sc:Canvas",
                    "label": "CTPC(a)0-57",
                    "metadata": [
                        {
                            "label": "Description",
                            "value": "[ <a href=\"https://suikeichu.web.app/item/CTPC(a)0-57\">籍田</a> ]<br/>分類：地点<br/>記号説明：亭台跡"
                        }
                    ],
                    "thumbnail": "https://iiif.dl.itc.u-tokyo.ac.jp/iiif/tmp/toyo/suikei/jouzu06_heijou.tif/1943,2737,87,145/200,/0/default.jpg"
                },
                {
                    "@id": "https://nakamura196.github.io/suikeichuuzu/iiif/jouzu06_heijou/manifest.json/canvas/p1#xywh=1848,2798,77,167",
                    "@type": "sc:Canvas",
                    "label": "CTPC(a)0-58",
                    "metadata": [
                        {
                            "label": "Description",
                            "value": "[ <a href=\"https://suikeichu.web.app/item/CTPC(a)0-58\">藥圃</a> ]<br/>分類：地点<br/>記号説明：亭台跡"
                        }
                    ],
                    "thumbnail": "https://iiif.dl.itc.u-tokyo.ac.jp/iiif/tmp/toyo/suikei/jouzu06_heijou.tif/1848,2798,77,167/200,/0/default.jpg"
                },
                {
                    "@id": "https://nakamura196.github.io/suikeichuuzu/iiif/jouzu06_heijou/manifest.json/canvas/p1#xywh=1717,2784,121,69",
                    "@type": "sc:Canvas",
                    "label": "CTPC(a)0-59",
                    "metadata": [
                        {
                            "label": "Description",
                            "value": "[ <a href=\"https://suikeichu.web.app/item/CTPC(a)0-59\">靈臺</a> ]<br/>分類：地点<br/>記号説明：亭台跡"
                        }
                    ],
                    "thumbnail": "https://iiif.dl.itc.u-tokyo.ac.jp/iiif/tmp/toyo/suikei/jouzu06_heijou.tif/1717,2784,121,69/200,/0/default.jpg"
                },
                {
                    "@id": "https://nakamura196.github.io/suikeichuuzu/iiif/jouzu06_heijou/manifest.json/canvas/p1#xywh=1703,2850,133,135",
                    "@type": "sc:Canvas",
                    "label": "CTPC(a)0-60",
                    "metadata": [
                        {
                            "label": "Description",
                            "value": "[ <a href=\"https://suikeichu.web.app/item/CTPC(a)0-60\">辟雍明堂</a> ]<br/>分類：地点<br/>記号説明：亭台跡"
                        }
                    ],
                    "thumbnail": "https://iiif.dl.itc.u-tokyo.ac.jp/iiif/tmp/toyo/suikei/jouzu06_heijou.tif/1703,2850,133,135/200,/0/default.jpg"
                },
                {
                    "@id": "https://nakamura196.github.io/suikeichuuzu/iiif/jouzu06_heijou/manifest.json/canvas/p1#xywh=1245,2953,187,111",
                    "@type": "sc:Canvas",
                    "label": "CTPC(a)0-61",
                    "metadata": [
                        {
                            "label": "Description",
                            "value": "[ <a href=\"https://suikeichu.web.app/item/CTPC(a)0-61\">郊郭</a> ]<br/>分類：なし<br/>記号説明："
                        }
                    ],
                    "thumbnail": "https://iiif.dl.itc.u-tokyo.ac.jp/iiif/tmp/toyo/suikei/jouzu06_heijou.tif/1245,2953,187,111/200,/0/default.jpg"
                },
                {
                    "@id": "https://nakamura196.github.io/suikeichuuzu/iiif/jouzu06_heijou/manifest.json/canvas/p1#xywh=1116,713,194,122",
                    "@type": "sc:Canvas",
                    "label": "CTPC(a)0-62",
                    "metadata": [
                        {
                            "label": "Description",
                            "value": "[ <a href=\"https://suikeichu.web.app/item/CTPC(a)0-62\">枝津</a> ]<br/>分類：地形<br/>記号説明：河川"
                        }
                    ],
                    "thumbnail": "https://iiif.dl.itc.u-tokyo.ac.jp/iiif/tmp/toyo/suikei/jouzu06_heijou.tif/1116,713,194,122/200,/0/default.jpg"
                }
            ],
            "within": {
                "@id": "https://nakamura196.github.io/suikeichuuzu/iiif/jouzu06_heijou/manifest.json",
                "@type": "sc:Manifest",
                "label": "jouzu06_heijou"
            }
        }
    ],
    "viewingHint": "annotation"
}